{"create_ts": "2020-09-06 07:34:27.302647", "task_id": "a36b47f9-7ae2-4af9-9bb8-a37ab10bc7b2", "version_id": "43c2f8f8-585e-43cb-afc9-b3b7df2c70bb", "task_name": "Entity and Extraction Reviews", "task_class": "xpms_lib_dag.tasks.dag_task.DagTask", "name": "base version", "description": "", "start": "StartEvent_f0f9926d-3bc9-4195-a05a-633ad25745ee", "end": "EndEvent_05s9zd7", "tasks": {"StartEvent_f0f9926d-3bc9-4195-a05a-633ad25745ee": {"solution_id": "newgit2", "task_name": "Dummy Task", "task_id": "dummy_task", "version_id": "PFX2znghSTir5gxWYifWgw", "task_class": "xpms_lib_dag.tasks.dummy_task.DummyTask", "name": "start", "description": "", "start": null, "end": null, "tasks": {}, "is_enabled": true, "config": {}, "exec_type": "sync", "category": "default.Base", "is_published": true, "is_deleted": false, "compatible_groups": ["base_dependency_group"], "extras": {"x_config": [{"options": ["any", "all"], "is_option_object": false, "display_key": null, "value_key": null, "name": "dependencies", "description": "dependency on previous tasks to run", "data_type": "string", "op_type": "categorical", "value": "any", "multi_select": false, "hidden": false, "config_path": "config.dependencies", "ui_component": "", "_XpmsObjectMixin__type": "CategoricalListConfiguration", "_XpmsObjectMixin__api_version": "1.0.13"}]}, "next": ["2dbdf8a2-7b76-48c3-ad74-03027547d10b", "ServiceTask_0vyvaro"], "previous": [], "timeout": 3000, "retries": 3, "instance_id": "_6Y9ubUNRfuMixtRixuYzQ", "cts": "", "uts": "", "default_version": "hsSA7ANnR7OUxm1JofsIbw", "created_by": "system", "modified_by": "system", "_XpmsObjectMixin__type": "TaskVersionBundle", "_XpmsObjectMixin__api_version": "10.0", "asset_source": {"type": "", "name": "", "version": ""}, "pulse_enabled": false}, "EndEvent_05s9zd7": {"solution_id": "newgit2", "task_name": "Dummy Task", "task_id": "dummy_task", "version_id": "PFX2znghSTir5gxWYifWgw", "task_class": "xpms_lib_dag.tasks.dummy_task.DummyTask", "name": "end", "description": "", "start": null, "end": null, "tasks": {}, "is_enabled": true, "config": {"conditions": {}}, "exec_type": "sync", "category": "default.Base", "is_published": true, "is_deleted": false, "compatible_groups": ["base_dependency_group"], "extras": {"x_config": [{"options": ["any", "all"], "is_option_object": false, "display_key": null, "value_key": null, "name": "dependencies", "description": "dependency on previous tasks to run", "data_type": "string", "op_type": "categorical", "value": "any", "multi_select": false, "hidden": false, "config_path": "config.dependencies", "ui_component": "", "_XpmsObjectMixin__type": "CategoricalListConfiguration", "_XpmsObjectMixin__api_version": "1.0.13"}]}, "next": [], "previous": ["ServiceTask_0dieep8"], "timeout": 3000, "retries": 3, "instance_id": "_6Y9ubUNRfuMixtRixuYzQ", "cts": "", "uts": "", "default_version": "hsSA7ANnR7OUxm1JofsIbw", "created_by": "system", "modified_by": "system", "_XpmsObjectMixin__type": "TaskVersionBundle", "_XpmsObjectMixin__api_version": "10.0", "asset_source": {"type": "", "name": "", "version": ""}, "pulse_enabled": false}, "ServiceTask_0vyvaro": {"solution_id": "newgit2", "task_name": "Review Task", "task_id": "eyLOKNOJTcmxoRnop6N8gA", "version_id": "default", "task_class": "xpms_lib_dag.tasks.user_review_task.UserReviewTask", "name": "Review Extraction Task", "description": "", "start": null, "end": null, "tasks": {}, "is_enabled": true, "config": {"conditions": {"StartEvent_f0f9926d-3bc9-4195-a05a-633ad25745ee": "inputs[\"document\"][0][\"metadata\"][\"properties\"][\"extension\"] in [\".xls\" ,\".xlsx\",\".csv\"]"}, "dependencies": "any", "service": {"configuration": {"doc_state": "review_extraction"}}}, "exec_type": "sync", "category": "services.User Task", "is_published": true, "is_deleted": false, "compatible_groups": ["base_dependency_group"], "extras": {"index": "services.review_task", "x_config": [{"options": ["any", "all"], "is_option_object": false, "display_key": null, "value_key": null, "name": "dependencies", "description": "dependency on previous tasks to run", "data_type": "string", "op_type": "categorical", "value": "any", "multi_select": false, "hidden": false, "config_path": "config.dependencies", "ui_component": "", "_XpmsObjectMixin__type": "CategoricalListConfiguration", "_XpmsObjectMixin__api_version": "1.0.13"}, {"options": ["review_classification", "review_extraction", "review_entity"], "is_option_object": false, "display_key": null, "value_key": null, "name": "Document State", "description": "", "data_type": "string", "op_type": "categorical", "value": "review_classification", "multi_select": false, "hidden": false, "config_path": "config.service.configuration.doc_state", "ui_component": "", "_XpmsObjectMixin__type": "CategoricalListConfiguration", "_XpmsObjectMixin__api_version": "1.0.13"}]}, "next": ["ServiceTask_1v2y8mh"], "previous": ["2dbdf8a2-7b76-48c3-ad74-03027547d10b", "StartEvent_f0f9926d-3bc9-4195-a05a-633ad25745ee"], "timeout": 3000, "retries": 3, "instance_id": "0hzBaCyfQjah8Z7W3SuWLw", "cts": "", "uts": "", "default_version": "vE7TLwcsQrqfq9Z5D-M0DA", "created_by": "system", "modified_by": "system", "_XpmsObjectMixin__type": "TaskVersionBundle", "_XpmsObjectMixin__api_version": "10.0", "asset_source": {"type": "", "name": "", "version": ""}, "pulse_enabled": false}, "ServiceTask_1v2y8mh": {"solution_id": "newgit2", "task_name": "Extract Document Entities", "task_id": "B_76MfrnQTm_Q4J3fZhFiA", "version_id": "default", "task_class": "xpms_lib_dag.tasks.mq_task.MqTask", "name": "Extract Document Entities", "description": "service to extract entities from a document", "start": null, "end": null, "tasks": {}, "is_enabled": true, "config": {"conditions": {}, "dependencies": "any"}, "exec_type": "sync", "category": "services.Entity Linking", "is_published": true, "is_deleted": false, "compatible_groups": ["base_dependency_group"], "extras": {"x_config": [{"options": ["any", "all"], "is_option_object": false, "display_key": null, "value_key": null, "name": "dependencies", "description": "dependency on previous tasks to run", "data_type": "string", "op_type": "categorical", "value": "any", "multi_select": false, "hidden": false, "config_path": "config.dependencies", "ui_component": "", "_XpmsObjectMixin__type": "CategoricalListConfiguration", "_XpmsObjectMixin__api_version": "1.0.13"}]}, "next": ["ServiceTask_0dieep8"], "previous": ["ServiceTask_0vyvaro"], "timeout": 240, "retries": 3, "instance_id": "dtkkKi1VTye4FU34JDjViA", "cts": "", "uts": "", "default_version": "v1", "created_by": "system", "modified_by": "system", "_XpmsObjectMixin__type": "TaskVersionBundle", "_XpmsObjectMixin__api_version": "10.0", "asset_source": {"type": "", "name": "", "version": ""}, "pulse_enabled": false}, "ServiceTask_0dieep8": {"solution_id": "newgit2", "task_name": "Review Task", "task_id": "eyLOKNOJTcmxoRnop6N8gA", "version_id": "default", "task_class": "xpms_lib_dag.tasks.user_review_task.UserReviewTask", "name": "Review Entity Task", "description": "", "start": null, "end": null, "tasks": {}, "is_enabled": true, "config": {"conditions": {}, "dependencies": "any", "service": {"configuration": {"doc_state": "review_entity"}}}, "exec_type": "sync", "category": "services.User Task", "is_published": true, "is_deleted": false, "compatible_groups": ["base_dependency_group"], "extras": {"index": "services.review_task", "x_config": [{"options": ["any", "all"], "is_option_object": false, "display_key": null, "value_key": null, "name": "dependencies", "description": "dependency on previous tasks to run", "data_type": "string", "op_type": "categorical", "value": "any", "multi_select": false, "hidden": false, "config_path": "config.dependencies", "ui_component": "", "_XpmsObjectMixin__type": "CategoricalListConfiguration", "_XpmsObjectMixin__api_version": "1.0.13"}, {"options": ["review_classification", "review_extraction", "review_entity"], "is_option_object": false, "display_key": null, "value_key": null, "name": "Document State", "description": "", "data_type": "string", "op_type": "categorical", "value": "review_classification", "multi_select": false, "hidden": false, "config_path": "config.service.configuration.doc_state", "ui_component": "", "_XpmsObjectMixin__type": "CategoricalListConfiguration", "_XpmsObjectMixin__api_version": "1.0.13"}]}, "next": ["EndEvent_05s9zd7"], "previous": ["ServiceTask_1v2y8mh"], "timeout": 3000, "retries": 3, "instance_id": "0hzBaCyfQjah8Z7W3SuWLw", "cts": "", "uts": "", "default_version": "vE7TLwcsQrqfq9Z5D-M0DA", "created_by": "system", "modified_by": "system", "_XpmsObjectMixin__type": "TaskVersionBundle", "_XpmsObjectMixin__api_version": "10.0", "asset_source": {"type": "", "name": "", "version": ""}, "pulse_enabled": false}, "2dbdf8a2-7b76-48c3-ad74-03027547d10b": {"solution_id": "impoerasset", "task_name": "Extract_text_group", "task_id": "2dbdf8a2-7b76-48c3-ad74-03027547d10b", "version_id": "default", "task_class": "xpms_lib_dag.tasks.dag_task.DagTask", "name": "Extract_text_group", "description": "", "start": "StartEvent_2f56fd4d-9e44-4824-92eb-139c32ee9602", "end": "EndEvent_0qrarhz", "tasks": {"StartEvent_2f56fd4d-9e44-4824-92eb-139c32ee9602": {"solution_id": "finaldefaultpipeline_91d219b1-7c3f-4679-bec6-1f9886616fc8", "task_name": "Dummy Task", "task_id": "dummy_task", "version_id": "I2LJX8w2SVS-mjC7EXCV7w", "task_class": "xpms_lib_dag.tasks.dummy_task.DummyTask", "name": "start", "description": "", "start": null, "end": null, "tasks": {}, "is_enabled": true, "config": {}, "exec_type": "sync", "category": "default", "is_published": true, "is_deleted": false, "compatible_groups": ["base_dependency_group"], "extras": {"x_config": [{"options": ["any", "all"], "is_option_object": false, "display_key": null, "value_key": null, "name": "dependencies", "description": "dependency on previous tasks to run", "data_type": "string", "op_type": "categorical", "value": "any", "multi_select": false, "hidden": false, "config_path": "config.dependencies", "ui_component": "", "_XpmsObjectMixin__type": "CategoricalListConfiguration", "_XpmsObjectMixin__api_version": "1.0.13"}]}, "next": ["Task_1la389c"], "previous": [], "timeout": 3000, "retries": 3, "instance_id": "M1t7488MTF-jNRTb_u1a1w"}, "EndEvent_0qrarhz": {"solution_id": "finaldefaultpipeline_91d219b1-7c3f-4679-bec6-1f9886616fc8", "task_name": "Dummy Task", "task_id": "dummy_task", "version_id": "I2LJX8w2SVS-mjC7EXCV7w", "task_class": "xpms_lib_dag.tasks.dummy_task.DummyTask", "name": "end", "description": "", "start": null, "end": null, "tasks": {}, "is_enabled": true, "config": {"conditions": {}}, "exec_type": "sync", "category": "default", "is_published": true, "is_deleted": false, "compatible_groups": ["base_dependency_group"], "extras": {"x_config": [{"options": ["any", "all"], "is_option_object": false, "display_key": null, "value_key": null, "name": "dependencies", "description": "dependency on previous tasks to run", "data_type": "string", "op_type": "categorical", "value": "any", "multi_select": false, "hidden": false, "config_path": "config.dependencies", "ui_component": "", "_XpmsObjectMixin__type": "CategoricalListConfiguration", "_XpmsObjectMixin__api_version": "1.0.13"}]}, "next": [], "previous": ["Task_1b2uzh2", "Task_18pvjhc"], "timeout": 3000, "retries": 3, "instance_id": "M1t7488MTF-jNRTb_u1a1w"}, "Task_1la389c": {"solution_id": "finaldefaultpipeline_91d219b1-7c3f-4679-bec6-1f9886616fc8", "task_name": "Generate Searchable Pdf Document", "task_id": "u-P--ZhaRwiFDhL7M-ngiA", "version_id": "default", "task_class": "xpms_lib_dag.tasks.mq_task.MqTask", "name": "Generate Searchable Pdf Document", "description": "service to generate searchable pdf from pages", "start": null, "end": null, "tasks": {}, "is_enabled": true, "config": {"conditions": {}, "dependencies": "any"}, "exec_type": "sync", "category": "services", "is_published": true, "is_deleted": false, "compatible_groups": ["base_dependency_group"], "extras": {"x_config": [{"options": ["any", "all"], "is_option_object": false, "display_key": null, "value_key": null, "name": "dependencies", "description": "dependency on previous tasks to run", "data_type": "string", "op_type": "categorical", "value": "any", "multi_select": false, "hidden": false, "config_path": "config.dependencies", "ui_component": "", "_XpmsObjectMixin__type": "CategoricalListConfiguration", "_XpmsObjectMixin__api_version": "1.0.13"}]}, "next": ["Task_0rtxh97", "Task_1m47bg4"], "previous": ["StartEvent_2f56fd4d-9e44-4824-92eb-139c32ee9602"], "timeout": 10, "retries": 3, "instance_id": "H22Dan8TROWutrNZlO74YQ"}, "Task_1m47bg4": {"solution_id": "finaldefaultpipeline_91d219b1-7c3f-4679-bec6-1f9886616fc8", "task_name": "Extract Paragraphs", "task_id": "bpXIWx0ESdyDwFRWIlOXVQ", "version_id": "default", "task_class": "xpms_lib_dag.tasks.mq_task.MqTask", "name": "Extract Paragraphs", "description": "Extract Paragraphs for each page of document.", "start": null, "end": null, "tasks": {}, "is_enabled": true, "config": {"conditions": {"Task_1la389c": "inputs[\"document\"][0][\"metadata\"][\"template_info\"][\"template_type\"] == \"unknown\""}, "dependencies": "any"}, "exec_type": "sync", "category": "services", "is_published": true, "is_deleted": false, "compatible_groups": ["base_dependency_group"], "extras": {"x_config": [{"options": ["any", "all"], "is_option_object": false, "display_key": null, "value_key": null, "name": "dependencies", "description": "dependency on previous tasks to run", "data_type": "string", "op_type": "categorical", "value": "any", "multi_select": false, "hidden": false, "config_path": "config.dependencies", "ui_component": "", "_XpmsObjectMixin__type": "CategoricalListConfiguration", "_XpmsObjectMixin__api_version": "1.0.13"}]}, "next": ["ServiceTask_1i63z9z"], "previous": ["Task_1la389c"], "timeout": 100, "retries": 3, "instance_id": "UyEMyRXiSs6yYLxCZbLVtQ"}, "Task_0rtxh97": {"solution_id": "finaldefaultpipeline_91d219b1-7c3f-4679-bec6-1f9886616fc8", "task_name": "Extract Document Structured Elements", "task_id": "n32fU1P6SiqBuq_l-gEJRg", "version_id": "default", "task_class": "xpms_lib_dag.tasks.mq_task.MqTask", "name": "Extract Document Structured Elements", "description": "service to extract structured elements from document", "start": null, "end": null, "tasks": {}, "is_enabled": true, "config": {"conditions": {"Task_1la389c": "inputs[\"document\"][0][\"metadata\"][\"template_info\"][\"template_type\"] == \"known\""}, "dependencies": "any"}, "exec_type": "sync", "category": "services", "is_published": true, "is_deleted": false, "compatible_groups": ["base_dependency_group"], "extras": {"x_config": [{"options": ["any", "all"], "is_option_object": false, "display_key": null, "value_key": null, "name": "dependencies", "description": "dependency on previous tasks to run", "data_type": "string", "op_type": "categorical", "value": "any", "multi_select": false, "hidden": false, "config_path": "config.dependencies", "ui_component": "", "_XpmsObjectMixin__type": "CategoricalListConfiguration", "_XpmsObjectMixin__api_version": "1.0.13"}]}, "next": ["Task_1b2uzh2"], "previous": ["Task_1la389c"], "timeout": 240, "retries": 3, "instance_id": "C2XQGrUIS96NZzUYo8y8gQ"}, "Task_1b2uzh2": {"solution_id": "finaldefaultpipeline_91d219b1-7c3f-4679-bec6-1f9886616fc8", "task_name": "Extract Document Text", "task_id": "HEvgbL9wRhGbKDyTlebf3A", "version_id": "default", "task_class": "xpms_lib_dag.tasks.mq_task.MqTask", "name": "Extract Document Text", "description": "service to extract text from slices", "start": null, "end": null, "tasks": {}, "is_enabled": true, "config": {"conditions": {}, "dependencies": "any"}, "exec_type": "sync", "category": "services", "is_published": true, "is_deleted": false, "compatible_groups": ["base_dependency_group"], "extras": {"x_config": [{"options": ["any", "all"], "is_option_object": false, "display_key": null, "value_key": null, "name": "dependencies", "description": "dependency on previous tasks to run", "data_type": "string", "op_type": "categorical", "value": "any", "multi_select": false, "hidden": false, "config_path": "config.dependencies", "ui_component": "", "_XpmsObjectMixin__type": "CategoricalListConfiguration", "_XpmsObjectMixin__api_version": "1.0.13"}]}, "next": ["EndEvent_0qrarhz"], "previous": ["Task_0rtxh97"], "timeout": 240, "retries": 3, "instance_id": "R_OZ5_hYREup7ZAQnSmm7Q"}, "Task_0rnq9lm": {"solution_id": "finaldefaultpipeline_91d219b1-7c3f-4679-bec6-1f9886616fc8", "task_name": "Extract Tables", "task_id": "c6-uSD4xShSjcna2-wmrfw", "version_id": "default", "task_class": "xpms_lib_dag.tasks.mq_task.MqTask", "name": "Extract Tables", "description": "Extract Tables for each page of document.", "start": null, "end": null, "tasks": {}, "is_enabled": true, "config": {"conditions": {}, "dependencies": "any", "data": {"configuration": {"known_table_headings": [null], "min_no_of_column_bordered_table": 2, "min_no_of_row_in_bordered_table": 2, "min_no_of_column_borderless_table": 2, "min_no_of_lines_borderless_table": 2}}}, "exec_type": "sync", "category": "services", "is_published": true, "is_deleted": false, "compatible_groups": ["base_dependency_group"], "extras": {"x_config": [{"options": ["any", "all"], "is_option_object": false, "display_key": null, "value_key": null, "name": "dependencies", "description": "dependency on previous tasks to run", "data_type": "string", "op_type": "categorical", "value": "any", "multi_select": false, "hidden": false, "config_path": "config.dependencies", "ui_component": "", "_XpmsObjectMixin__type": "CategoricalListConfiguration", "_XpmsObjectMixin__api_version": "1.0.13"}, {"name": "known Table Headers", "description": "known Table Headers", "data_type": ["string", "integer", "float", "boolean", "object"], "op_type": "continuous", "value": null, "multi_select": true, "hidden": false, "config_path": "config.data.configuration.known_table_headings", "ui_component": "", "_XpmsObjectMixin__type": "StringConfiguration", "_XpmsObjectMixin__api_version": "1.0.13"}, {"min_value": 1, "max_value": 100, "closure": "closed_closed", "name": "Min No Row In Bordered Table", "description": "min no. of column defined in table", "data_type": "integer", "op_type": "continuous", "value": 2, "multi_select": false, "hidden": false, "config_path": "config.data.configuration.min_no_of_column_bordered_table", "ui_component": "", "_XpmsObjectMixin__type": "NumericConfiguration", "_XpmsObjectMixin__api_version": "1.0.13"}, {"min_value": 1, "max_value": 100, "closure": "closed_closed", "name": "Min No Column In Table", "description": "min no. of row defined in table", "data_type": "integer", "op_type": "continuous", "value": 2, "multi_select": false, "hidden": false, "config_path": "config.data.configuration.min_no_of_row_in_bordered_table", "ui_component": "", "_XpmsObjectMixin__type": "NumericConfiguration", "_XpmsObjectMixin__api_version": "1.0.13"}, {"min_value": 1, "max_value": 10, "closure": "closed_closed", "name": "Min No Row In Borderless Table", "description": "min no. of column defined in table", "data_type": "integer", "op_type": "continuous", "value": 2, "multi_select": false, "hidden": false, "config_path": "config.data.configuration.min_no_of_column_borderless_table", "ui_component": "", "_XpmsObjectMixin__type": "NumericConfiguration", "_XpmsObjectMixin__api_version": "1.0.13"}, {"min_value": 1, "max_value": 1000, "closure": "closed_closed", "name": "Min No Lines In Borderless Table", "description": "min no. of lines defined in table", "data_type": "integer", "op_type": "continuous", "value": 2, "multi_select": false, "hidden": false, "config_path": "config.data.configuration.min_no_of_lines_borderless_table", "ui_component": "", "_XpmsObjectMixin__type": "NumericConfiguration", "_XpmsObjectMixin__api_version": "1.0.13"}]}, "next": ["Task_0ejth3b"], "previous": ["ServiceTask_1i63z9z"], "timeout": 100, "retries": 3, "instance_id": "AFzxM1pOR3SGHdp9alQduw"}, "Task_0ejth3b": {"solution_id": "finaldefaultpipeline_91d219b1-7c3f-4679-bec6-1f9886616fc8", "task_name": "Extract Sentences", "task_id": "UO1MyB86RYOGx7EjqEkNUw", "version_id": "default", "task_class": "xpms_lib_dag.tasks.mq_task.MqTask", "name": "Extract Sentences", "description": "Extract sentences for each page of document.", "start": null, "end": null, "tasks": {}, "is_enabled": true, "config": {"conditions": {}, "dependencies": "any"}, "exec_type": "sync", "category": "services", "is_published": true, "is_deleted": false, "compatible_groups": ["base_dependency_group"], "extras": {"x_config": [{"options": ["any", "all"], "is_option_object": false, "display_key": null, "value_key": null, "name": "dependencies", "description": "dependency on previous tasks to run", "data_type": "string", "op_type": "categorical", "value": "any", "multi_select": false, "hidden": false, "config_path": "config.dependencies", "ui_component": "", "_XpmsObjectMixin__type": "CategoricalListConfiguration", "_XpmsObjectMixin__api_version": "1.0.13"}]}, "next": ["Task_0tztbaj"], "previous": ["Task_0rnq9lm"], "timeout": 100, "retries": 3, "instance_id": "gNHrxTqbSCGWQkBjsHveiA"}, "Task_0tztbaj": {"solution_id": "finaldefaultpipeline_91d219b1-7c3f-4679-bec6-1f9886616fc8", "task_name": "Aggregate Elements", "task_id": "tHbWqkZQT0i0fTSrJ-6FHA", "version_id": "default", "task_class": "xpms_lib_dag.tasks.mq_task.MqTask", "name": "Aggregate Elements", "description": "Aggregate Elements across pages of document.", "start": null, "end": null, "tasks": {}, "is_enabled": true, "config": {"conditions": {}, "dependencies": "any"}, "exec_type": "sync", "category": "services", "is_published": true, "is_deleted": false, "compatible_groups": ["base_dependency_group"], "extras": {"x_config": [{"options": ["any", "all"], "is_option_object": false, "display_key": null, "value_key": null, "name": "dependencies", "description": "dependency on previous tasks to run", "data_type": "string", "op_type": "categorical", "value": "any", "multi_select": false, "hidden": false, "config_path": "config.dependencies", "ui_component": "", "_XpmsObjectMixin__type": "CategoricalListConfiguration", "_XpmsObjectMixin__api_version": "1.0.13"}]}, "next": ["Task_18pvjhc"], "previous": ["Task_0ejth3b"], "timeout": 100, "retries": 3, "instance_id": "rmIZcMSCQ2yzTdz5dY5oKQ"}, "Task_18pvjhc": {"solution_id": "finaldefaultpipeline_91d219b1-7c3f-4679-bec6-1f9886616fc8", "task_name": "Extract Document Elements", "task_id": "RSx__cmcQjqpP3EkKb8ojg", "version_id": "default", "task_class": "xpms_lib_dag.tasks.mq_task.MqTask", "name": "Extract Document Elements", "description": "service to extract elements from document", "start": null, "end": null, "tasks": {}, "is_enabled": true, "config": {"conditions": {}, "dependencies": "any"}, "exec_type": "sync", "category": "services", "is_published": true, "is_deleted": false, "compatible_groups": ["base_dependency_group"], "extras": {"x_config": [{"options": ["any", "all"], "is_option_object": false, "display_key": null, "value_key": null, "name": "dependencies", "description": "dependency on previous tasks to run", "data_type": "string", "op_type": "categorical", "value": "any", "multi_select": false, "hidden": false, "config_path": "config.dependencies", "ui_component": "", "_XpmsObjectMixin__type": "CategoricalListConfiguration", "_XpmsObjectMixin__api_version": "1.0.13"}]}, "next": ["EndEvent_0qrarhz"], "previous": ["Task_0tztbaj"], "timeout": 240, "retries": 3, "instance_id": "JgpxHkiPTtSYGRbojo6EEQ"}, "ServiceTask_1i63z9z": {"solution_id": "finaldefaultpipeline_91d219b1-7c3f-4679-bec6-1f9886616fc8", "task_name": "Extract Fields", "task_id": "Xv-Sv-OCSs2rMnp7jrlH3w", "version_id": "default", "task_class": "xpms_lib_dag.tasks.mq_task.MqTask", "name": "Extract Fields", "description": "Extract Fields for each page of document.", "start": null, "end": null, "tasks": {}, "is_enabled": true, "config": {"conditions": {}, "dependencies": "any", "data": {"configuration": {"known_keys": ["null"], "max_gap_between_key_and_value": 10, "sentence_separator": ["|", ";"], "fields_separator": [":", "?", "#"]}}}, "exec_type": "sync", "category": "services", "is_published": true, "is_deleted": false, "compatible_groups": ["base_dependency_group"], "extras": {"x_config": [{"options": ["any", "all"], "is_option_object": false, "display_key": null, "value_key": null, "name": "dependencies", "description": "dependency on previous tasks to run", "data_type": "string", "op_type": "categorical", "value": "any", "multi_select": false, "hidden": false, "config_path": "config.dependencies", "ui_component": "", "_XpmsObjectMixin__type": "CategoricalListConfiguration", "_XpmsObjectMixin__api_version": "1.0.13"}, {"name": "known Keys", "description": "known keys", "data_type": "string", "op_type": "continuous", "value": null, "multi_select": true, "hidden": false, "config_path": "config.data.configuration.known_keys", "ui_component": "", "_XpmsObjectMixin__type": "StringConfiguration", "_XpmsObjectMixin__api_version": "1.0.13"}, {"min_value": 10, "max_value": 100, "closure": "closed_closed", "name": "Key Value Distance", "description": "Max gap between key and value", "data_type": "integer", "op_type": "continuous", "value": 10, "multi_select": false, "hidden": false, "config_path": "config.data.configuration.max_gap_between_key_and_value", "ui_component": "", "_XpmsObjectMixin__type": "NumericConfiguration", "_XpmsObjectMixin__api_version": "1.0.13"}, {"name": "Sentences Separator", "description": "separator to split phrases for sentences", "data_type": "string", "op_type": "continuous", "value": ["|", ";"], "multi_select": true, "hidden": false, "config_path": "config.data.configuration.sentence_separator", "ui_component": "", "_XpmsObjectMixin__type": "StringConfiguration", "_XpmsObjectMixin__api_version": "1.0.13"}, {"name": "Fields Separator", "description": "separator to split phrases for Fields", "data_type": "string", "op_type": "continuous", "value": [":", "?", "#"], "multi_select": true, "hidden": false, "config_path": "config.data.configuration.fields_separator", "ui_component": "", "_XpmsObjectMixin__type": "StringConfiguration", "_XpmsObjectMixin__api_version": "1.0.13"}]}, "next": ["Task_0rnq9lm"], "previous": ["Task_1m47bg4"], "timeout": 100, "retries": 3, "instance_id": "OzmZTSb1QJa0BXmiHa6ufw"}}, "is_enabled": true, "config": {"conditions": {"StartEvent_f0f9926d-3bc9-4195-a05a-633ad25745ee": "inputs[\"document\"][0][\"metadata\"][\"properties\"][\"extension\"] not in [\".xls\" ,\".xlsx\",\".csv\"]"}}, "exec_type": "sync", "category": "pipeline", "is_published": true, "is_deleted": false, "compatible_groups": ["base_dependency_group"], "extras": {}, "next": ["ServiceTask_0vyvaro"], "previous": ["StartEvent_f0f9926d-3bc9-4195-a05a-633ad25745ee"], "timeout": 3000, "retries": 3, "instance_id": "RVHdkNmgQVCPsUkmc89gDA", "cts": "2019-07-19T12:42:23.664320", "uts": "2019-07-19T12:42:23.664329", "default_version": "6bf32518-0608-45b3-a80d-5591264ab233", "created_by": "system", "modified_by": "system", "_XpmsObjectMixin__type": "TaskVersionBundle", "_XpmsObjectMixin__api_version": "9.0"}}, "config": {}, "exec_type": null, "category": "pipeline", "is_enabled": true, "is_published": true, "is_deleted": false, "compatible_groups": ["base_dependency_group"], "extras": {}, "next": [], "previous": [], "timeout": 3000, "retries": 3, "state": {}, "instance_id": "Q5bxFgMpSUeYcS6zeenvPw", "created_by": "system", "modified_by": "system", "cts": "", "uts": "", "_XpmsObjectMixin__type": "Task", "_XpmsObjectMixin__api_version": "9.0"}