{
    "pipeline_id": "8bdb864e-311f-4c16-8070-85b459d22d46",
    "input_schema": {},
    "output_schema": {},
    "is_enabled": true,
    "category": "pipeline",
    "name": "internal_annotate_ingest",
    "description": "this pipeline internally ingests documents to annotate",
    "cts": "2020-02-17T12:24:59.558304",
    "is_deleted": false,
    "uts": "2020-02-17T12:33:03.398709",
    "default_version": "639e98d4-e5f6-4862-b813-c4e6966b2667",
    "created_by": "system",
    "modified_by": "system",
    "_XpmsObjectMixin__type": "Pipeline",
    "_XpmsObjectMixin__api_version": "9.0",
    "generate_api": true
}